netify/__init__.py
netify/app.py
netify/config.py
netify/template.py
netify/view.py
netify-0.2.dist-info/DESCRIPTION.rst
netify-0.2.dist-info/METADATA
netify-0.2.dist-info/RECORD
netify-0.2.dist-info/WHEEL
netify-0.2.dist-info/entry_points.txt
netify-0.2.dist-info/metadata.json
netify-0.2.dist-info/top_level.txt
netify-0.2.dist-info/zip-safe
