Metadata-Version: 2.0
Name: netify
Version: 0.2
Summary: Turn boring things into something for the net.
Home-page: https://github.com/fretboardfreak/netify
Author: Curtis Sand
Author-email: curtissand@gmail.com
License: Apache
Keywords: net netify app webapp html site website generator
Platform: UNKNOWN
Classifier: Development Status :: 3 - Alpha
Classifier: License :: OSI Approved :: Apache Software License
Classifier: Intended Audience :: Developers
Classifier: Framework :: Flask
Classifier: Environment :: Web Environment
Classifier: Operating System :: POSIX :: Linux
Classifier: Operating System :: MacOS
Classifier: Programming Language :: Python :: 3
Classifier: Programming Language :: Python :: 3 :: Only
Classifier: Topic :: Internet
Classifier: Topic :: Internet :: WWW/HTTP
Classifier: Topic :: Internet :: WWW/HTTP :: Dynamic Content
Classifier: Topic :: Internet :: WWW/HTTP :: Site Management
Classifier: Topic :: Software Development
Classifier: Topic :: Software Development :: Libraries
Classifier: Topic :: Software Development :: Libraries :: Application Frameworks
Requires-Dist: Flask (==0.11.1)
Requires-Dist: Flask-Classy (==0.6.10)
Requires-Dist: Jinja2 (==2.8)
Requires-Dist: MarkupSafe (==0.23)
Requires-Dist: Werkzeug (==0.11.11)
Requires-Dist: click (==6.6)
Requires-Dist: itsdangerous (==0.24)
Requires-Dist: yattag (==1.6.0)
